{"repo": {"timestamp": 1742666464000, "version": 20000, "name": "magamajo", "icon": "icon.png", "address": "https://raw.githubusercontent.com/MaximilienNaveau/magamajo/master/fdroid/repo", "description": "Private repos of Magamajo", "mirrors": ["https://localhost/repos/YaymDI6tcjzGW06x0v-C5PmLGKkhrWO_/repo/repo", "https://raw.githubusercontent.com/MaximilienNaveau/magamajo/master/fdroid/repo/repo"]}, "requests": {"install": [], "uninstall": []}, "apps": [{"suggestedVersionCode": "1713557789", "license": "Unknown", "name": "rob_transparent", "added": 1713557789000, "packageName": "rob_transparent", "lastUpdated": 1742666464000}, {"authorName": "Magamajo", "categories": ["Games"], "suggestedVersionCode": "1", "license": "Unknown", "name": "trampoline", "added": 1742661101000, "packageName": "com.magamajo.trampoline", "lastUpdated": 1742666464000, "localized": {"en-US": {"description": "Faire 13 anagrammes de 9 lettres avec les lettres jaunes disponibles. Chaque lettre poss\u00e8de une lettre secondaire verte en g\u00e9n\u00e9rale. Si vous utilisez les vertes vous aurez plus de choix mais moins de points.\r\n\r\nAlors maintenant on dit: d\u00e9sol\u00e9 samedi j'ai trampoline ;)", "summary": "Un jeu pour faire rebomdir les mots."}}}], "packages": {"com.magamajo.trampoline": [{"added": 1742662916000, "apkName": "trampoline_3.1.0.apk", "hash": "1f1077458c043beb3164825c962352b7f0b9cc995ba970b7f9925c82e46e88d6", "hashType": "sha256", "minSdkVersion": 24, "nativecode": ["armeabi-v7a"], "packageName": "com.magamajo.trampoline", "sig": "a13e3f11e5d7f569655902c69e2005b8", "signer": "52dba92e9943decbf2f130effa905ff038a5657891823c8a4646d58e2c0259c7", "size": 23158112, "targetSdkVersion": 34, "versionCode": 1, "versionName": "3.1.0"}, {"added": 1742663820000, "apkName": "trampoline_3.1.0_T2gSOtg.apk", "hash": "f6617ba70f79454216552c6b7b1219c9e01358bc282b3c91d657da7700a2922c", "hashType": "sha256", "minSdkVersion": 29, "nativecode": ["armeabi-v7a"], "packageName": "com.magamajo.trampoline", "sig": "a13e3f11e5d7f569655902c69e2005b8", "signer": "52dba92e9943decbf2f130effa905ff038a5657891823c8a4646d58e2c0259c7", "size": 23247760, "targetSdkVersion": 34, "versionCode": 1, "versionName": "3.1.0"}, {"added": 1742666464000, "apkName": "trampoline_3.1.0_kw4ko4J.apk", "hash": "c21a22bb0ea3310004b3320c9ca32edb252ef01cf0721cfd82c0566733222523", "hashType": "sha256", "minSdkVersion": 29, "nativecode": ["arm64-v8a", "armeabi-v7a"], "packageName": "com.magamajo.trampoline", "sig": "a13e3f11e5d7f569655902c69e2005b8", "signer": "52dba92e9943decbf2f130effa905ff038a5657891823c8a4646d58e2c0259c7", "size": 38722818, "targetSdkVersion": 34, "versionCode": 1, "versionName": "3.1.0"}, {"added": 1742663439000, "apkName": "trampoline_3.1.0_uTVB06f.apk", "hash": "d7f0e9108272d843b03b00120db01764ccbcc1c46d4d33ef730dad6756f77a76", "hashType": "sha256", "minSdkVersion": 34, "nativecode": ["armeabi-v7a"], "packageName": "com.magamajo.trampoline", "sig": "a13e3f11e5d7f569655902c69e2005b8", "signer": "52dba92e9943decbf2f130effa905ff038a5657891823c8a4646d58e2c0259c7", "size": 23242136, "targetSdkVersion": 34, "versionCode": 1, "versionName": "3.1.0"}], "rob_transparent": [{"added": 1742666464000, "apkName": "rob_transparent.png", "hash": "f100451a2c2f3dec46e2f62acdf3d98e1465d0806dfa7f0f302f72e0aced705a", "hashType": "sha256", "packageName": "rob_transparent", "size": 936869, "versionCode": 1713557789, "versionName": "2024-04-19"}]}}